mylib_021/__init__.py
mylib_021-0.1.dist-info/LICENSE.txt
mylib_021-0.1.dist-info/METADATA
mylib_021-0.1.dist-info/WHEEL
mylib_021-0.1.dist-info/top_level.txt
mylib_021-0.1.dist-info/RECORD
